pyexcept/__init__.py
pyexcept/_main.py
pyexcept-0.0.5.dist-info/METADATA
pyexcept-0.0.5.dist-info/WHEEL
pyexcept-0.0.5.dist-info/licenses/LICENSE
pyexcept-0.0.5.dist-info/RECORD
