Metadata-Version: 2.1
Name: pyexcept
Version: 0.0.5
Summary: Create custom new exceptions, choose from existing exceptions, raise your custom exceptions and messages, and more!
Project-URL: Homepage, https://github.com/Minetezter/pyexcept
Project-URL: Bug Tracker, https://github.com/Minetezter/pyexcept/issues
Author-email: minetezter <minetezter@protonmail.net>
License-File: LICENSE
Classifier: License :: OSI Approved :: GNU Affero General Public License v3 or later (AGPLv3+)
Classifier: Operating System :: POSIX :: Linux
Classifier: Programming Language :: Python :: 3
Requires-Python: >=3.7
